cosbr/__init__.py
cosbr/gcp_module.cpython-312-darwin.so
cosbr-0.1.1.dist-info/LICENSE
cosbr-0.1.1.dist-info/METADATA
cosbr-0.1.1.dist-info/WHEEL
cosbr-0.1.1.dist-info/top_level.txt
cosbr-0.1.1.dist-info/RECORD
