Metadata-Version: 2.2
Name: cosbr
Version: 0.1.1
Summary: Solver using Simulated Bifurcation
Home-page: https://github.com/yourusername/cosbr
Author: Your Name
Author-email: your.email@example.com
Classifier: Development Status :: 3 - Alpha
Classifier: Intended Audience :: Science/Research
Classifier: License :: OSI Approved :: MIT License
Classifier: Programming Language :: Python :: 3
Classifier: Programming Language :: C++
Classifier: Topic :: Scientific/Engineering
Classifier: Topic :: Scientific/Engineering :: Mathematics
Requires-Python: >=3.6
License-File: LICENSE
Requires-Dist: pybind11>=2.5.0
Requires-Dist: numpy
Dynamic: author
Dynamic: author-email
Dynamic: classifier
Dynamic: description
Dynamic: description-content-type
Dynamic: home-page
Dynamic: requires-dist
Dynamic: requires-python
Dynamic: summary
